nonebot_plugin_animalVoice/__init__.py
nonebot_plugin_animalVoice/AnimalVoice/__init__.py
nonebot_plugin_animalVoice/AnimalVoice/converter.py
nonebot_plugin_animalVoice/animalvoice_main.py
nonebot_plugin_animalVoice/Cheru/__init__.py
nonebot_plugin_animalVoice/cheru_main.py
nonebot_plugin_animalVoice/config.py
nonebot_plugin_animalvoice-0.2.2.dist-info/LICENSE
nonebot_plugin_animalvoice-0.2.2.dist-info/WHEEL
nonebot_plugin_animalvoice-0.2.2.dist-info/METADATA
nonebot_plugin_animalvoice-0.2.2.dist-info/RECORD
