Metadata-Version: 2.1
Name: nonebot-plugin-animalvoice
Version: 0.2.2
Summary: ✨Nonebot兽语译者插件✨
License: GPLv3
Author: angjustinl
Author-email: angjustin@163.com
Requires-Python: >=3.7,<4.0
Classifier: License :: Other/Proprietary License
Classifier: Programming Language :: Python :: 3
Classifier: Programming Language :: Python :: 3.7
Classifier: Programming Language :: Python :: 3.8
Classifier: Programming Language :: Python :: 3.9
Classifier: Programming Language :: Python :: 3.10
Classifier: Programming Language :: Python :: 3.11
Requires-Dist: nonebot2 (>=2.2.0,<3.0.0)
